[
    {
        "name": "Kernkraft 400",
        "artists": [
            "Zombie Nation"
        ],
        "id": "6PUzxtIHkv346yP89NzP9X",
        "album": "Kernkraft 400 Single Mixes",
        "duration": 285,
        "tempo": 140.064,
        "time_signature": 4,
        "energy": 0.43,
        "happiness": 0.487,
        "loudness": -7.839,
        "danceability": 0.798
    },
    {
        "name": "Heads Will Roll - A-Trak Remix",
        "artists": [
            "Yeah Yeah Yeahs",
            "A-Trak"
        ],
        "id": "2idmlkd8oUaQvYEtINpLBX",
        "album": "Heads Will Roll",
        "duration": 383,
        "tempo": 131.994,
        "time_signature": 4,
        "energy": 0.614,
        "happiness": 0.774,
        "loudness": -3.908,
        "danceability": 0.744
    },
    {
        "name": "Creep - BYOR Remix",
        "artists": [
            "Naeleck",
            "Haley Reinhart",
            "BYOR"
        ],
        "id": "41TkFhNYljV7omolLJ6Squ",
        "album": "Creep (BYOR Remix)",
        "duration": 156,
        "tempo": 126.979,
        "time_signature": 4,
        "energy": 0.775,
        "happiness": 0.435,
        "loudness": -6.539,
        "danceability": 0.696
    },
    {
        "name": "Rain on Me",
        "artists": [
            "FIXL",
            "Ruxolf",
            "Koa"
        ],
        "id": "1ymVJxxBnFgNM9ocMzVqSg",
        "album": "Rain on Me",
        "duration": 139,
        "tempo": 123.102,
        "time_signature": 4,
        "energy": 0.778,
        "happiness": 0.494,
        "loudness": -6.102,
        "danceability": 0.65
    },
    {
        "name": "Wake Me Up",
        "artists": [
            "Avicii"
        ],
        "id": "4h8VwCb1MTGoLKueQ1WgbD",
        "album": "True",
        "duration": 247,
        "tempo": 124.08,
        "time_signature": 4,
        "energy": 0.783,
        "happiness": 0.643,
        "loudness": -5.697,
        "danceability": 0.532
    },
    {
        "name": "Promises - Skrillex & Nero Remix",
        "artists": [
            "NERO"
        ],
        "id": "7569Hbv0FUS7vjkdGvdgeZ",
        "album": "Welcome Reality +",
        "duration": 268,
        "tempo": 140.02,
        "time_signature": 4,
        "energy": 0.819,
        "happiness": 0.143,
        "loudness": -3.374,
        "danceability": 0.527
    },
    {
        "name": "Tsunami - Original Mix",
        "artists": [
            "DVBBS",
            "Borgeous"
        ],
        "id": "3felG0BIvmmOoCIeE2A5vq",
        "album": "Tsunami (Original Mix)",
        "duration": 236,
        "tempo": 128.004,
        "time_signature": 4,
        "energy": 0.838,
        "happiness": 0.289,
        "loudness": -5.371,
        "danceability": 0.698
    },
    {
        "name": "All Around The World (La La La)",
        "artists": [
            "R3HAB",
            "A Touch Of Class"
        ],
        "id": "1D2Aldrksl9yWWCIPOeDzy",
        "album": "All Around The World (La La La)",
        "duration": 147,
        "tempo": 124.948,
        "time_signature": 4,
        "energy": 0.859,
        "happiness": 0.52,
        "loudness": -5.03,
        "danceability": 0.733
    },
    {
        "name": "I Feel The Magic",
        "artists": [
            "Lucky Luke",
            "Naeleck",
            "ZHIKO"
        ],
        "id": "0ic0iGmElvGLyYcITm3Yod",
        "album": "I Feel The Magic",
        "duration": 167,
        "tempo": 140.034,
        "time_signature": 4,
        "energy": 0.941,
        "happiness": 0.537,
        "loudness": -5.475,
        "danceability": 0.738
    },
    {
        "name": "Get Up (Rattle) [feat. Far East Movement] - Vocal Edit",
        "artists": [
            "Bingo Players",
            "Far East Movement"
        ],
        "id": "3wLPRjw2XQpmowqXUXb3UF",
        "album": "Get Up (Rattle) [feat. Far East Movement]",
        "duration": 166,
        "tempo": 127.99,
        "time_signature": 4,
        "energy": 0.985,
        "happiness": 0.72,
        "loudness": -2.69,
        "danceability": 0.801
    }
]